taipy/__init__.py
taipy/core/__init__.py
taipy/core/_core.py
taipy/core/_core_cli.py
taipy/core/_init.py
taipy/core/taipy.py
taipy/core/version.json
taipy/core/_backup/__init__.py
taipy/core/_backup/_backup.py
taipy/core/_entity/__init__.py
taipy/core/_entity/_dag.py
taipy/core/_entity/_entity.py
taipy/core/_entity/_entity_ids.py
taipy/core/_entity/_labeled.py
taipy/core/_entity/_properties.py
taipy/core/_entity/_reload.py
taipy/core/_entity/_submittable.py
taipy/core/_manager/__init__.py
taipy/core/_manager/_manager.py
taipy/core/_manager/_manager_factory.py
taipy/core/_orchestrator/__init__.py
taipy/core/_orchestrator/_abstract_orchestrator.py
taipy/core/_orchestrator/_orchestrator.py
taipy/core/_orchestrator/_orchestrator_factory.py
taipy/core/_orchestrator/utils.py
taipy/core/_orchestrator/_dispatcher/__init__.py
taipy/core/_orchestrator/_dispatcher/_development_job_dispatcher.py
taipy/core/_orchestrator/_dispatcher/_job_dispatcher.py
taipy/core/_orchestrator/_dispatcher/_standalone_job_dispatcher.py
taipy/core/_repository/__init__.py
taipy/core/_repository/_filesystem_repository.py
taipy/core/_repository/_repository.py
taipy/core/_repository/_repository_adapter.py
taipy/core/_repository/_repository_factory.py
taipy/core/_repository/_sql_model.py
taipy/core/_repository/_sql_repository.py
taipy/core/_version/__init__.py
taipy/core/_version/_utils.py
taipy/core/_version/_version.py
taipy/core/_version/_version_fs_repository.py
taipy/core/_version/_version_manager.py
taipy/core/_version/_version_manager_factory.py
taipy/core/_version/_version_model.py
taipy/core/_version/_version_repository.py
taipy/core/_version/_version_repository_factory.py
taipy/core/_version/_version_sql_repository.py
taipy/core/_version/_cli/__init__.py
taipy/core/_version/_cli/_bcolor.py
taipy/core/_version/_cli/_version_cli.py
taipy/core/common/__init__.py
taipy/core/common/_listattributes.py
taipy/core/common/_repr_enum.py
taipy/core/common/_utils.py
taipy/core/common/_warnings.py
taipy_core-2.4.0.dist-info/LICENSE
taipy_core-2.4.0.dist-info/METADATA
taipy_core-2.4.0.dist-info/WHEEL
taipy_core-2.4.0.dist-info/top_level.txt
taipy_core-2.4.0.dist-info/RECORD
