Metadata-Version: 2.1
Name: taipy-core
Version: 2.4.0
Summary: A Python library to build powerful and customized data-driven back-end applications.
Home-page: https://github.com/avaiga/taipy-core
Author: Avaiga
Author-email: dev@taipy.io
License: Apache License 2.0
Keywords: taipy-core
Classifier: Intended Audience :: Developers
Classifier: License :: OSI Approved :: Apache Software License
Classifier: Natural Language :: English
Classifier: Programming Language :: Python :: 3
Classifier: Programming Language :: Python :: 3.8
Classifier: Programming Language :: Python :: 3.9
Classifier: Programming Language :: Python :: 3.10
Classifier: Programming Language :: Python :: 3.11
Requires-Python: >=3.8
Provides-Extra: fastparquet
Provides-Extra: mssql
Provides-Extra: mysql
Provides-Extra: postgresql
License-File: LICENSE
